delegate/__init__.py
delegate_property-0.1.0.dist-info/LICENSE
delegate_property-0.1.0.dist-info/METADATA
delegate_property-0.1.0.dist-info/WHEEL
delegate_property-0.1.0.dist-info/top_level.txt
delegate_property-0.1.0.dist-info/RECORD
