Metadata-Version: 2.1
Name: delegate-property
Version: 0.1.0
Summary: delegate attributes of a class to another attribute's properties
Home-page: https://github.com/dscottboggs/python-delegate
Author: D. Scott Boggs
Author-email: scott@tams.tech
License: UNKNOWN
Platform: UNKNOWN
Classifier: Development Status :: 4 - Beta
Classifier: Intended Audience :: Developers
Classifier: License :: OSI Approved :: MIT License
Classifier: Programming Language :: Python
Classifier: Topic :: Software Development :: Libraries :: Python Modules
Classifier: Topic :: Software Development :: Code Generators
